pytrws/__init__.py
pytrws/cli.py
pytrws/core/__init__.py
pytrws/core/translator.py
pytrws/loaders/__init__.py
pytrws/loaders/base_loader.py
pytrws/loaders/legacy_loader.py
pytrws/loaders/python_loader.py
pytrws/utils/__init__.py
pytrws/utils/formatter.py
pytrws/utils/system.py
pytrws-0.1.0.dist-info/METADATA
pytrws-0.1.0.dist-info/WHEEL
pytrws-0.1.0.dist-info/entry_points.txt
pytrws-0.1.0.dist-info/top_level.txt
pytrws-0.1.0.dist-info/RECORD
